multiserialviewer/__init__.py
multiserialviewer/__main__.py
multiserialviewer/__version__.py
multiserialviewer/application/__init__.py
multiserialviewer/application/application.py
multiserialviewer/application/counterHandler.py
multiserialviewer/application/counterTableModel.py
multiserialviewer/application/proxyStyle.py
multiserialviewer/application/serialViewerController.py
multiserialviewer/application/serialViewerControllerPool.py
multiserialviewer/application/statisticsHandler.py
multiserialviewer/application/statisticsTableModel.py
multiserialviewer/application/watchHandler.py
multiserialviewer/application/watchTableModel.py
multiserialviewer/gui_main/__init__.py
multiserialviewer/gui_main/mainWindow.py
multiserialviewer/gui_main/settingsDialog.py
multiserialviewer/gui_viewer/__init__.py
multiserialviewer/gui_viewer/autoscrollHandler.py
multiserialviewer/gui_viewer/counterWidget.py
multiserialviewer/gui_viewer/searchHandler.py
multiserialviewer/gui_viewer/searchWidget.py
multiserialviewer/gui_viewer/serialViewerCreateDialog.py
multiserialviewer/gui_viewer/serialViewerSettingsWidget.py
multiserialviewer/gui_viewer/serialViewerTextEdit.py
multiserialviewer/gui_viewer/serialViewerWindow.py
multiserialviewer/gui_viewer/statisticsWidget.py
multiserialviewer/gui_viewer/watchWidget.py
multiserialviewer/icons/__init__.py
multiserialviewer/icons/iconSet.py
multiserialviewer/icons/google/README_ICONS.txt
multiserialviewer/icons/google/434343/add.png
multiserialviewer/icons/google/434343/app.png
multiserialviewer/icons/google/434343/capture_start.png
multiserialviewer/icons/google/434343/capture_stop.png
multiserialviewer/icons/google/434343/clear.png
multiserialviewer/icons/google/434343/counter.png
multiserialviewer/icons/google/434343/error.png
multiserialviewer/icons/google/434343/folder.png
multiserialviewer/icons/google/434343/highlighter.png
multiserialviewer/icons/google/434343/search.png
multiserialviewer/icons/google/434343/serial_viewer.png
multiserialviewer-25.9.0.dist-info/METADATA
multiserialviewer-25.9.0.dist-info/WHEEL
multiserialviewer-25.9.0.dist-info/entry_points.txt
multiserialviewer-25.9.0.dist-info/licenses/LICENSE
multiserialviewer-25.9.0.dist-info/RECORD
