Metadata-Version: 2.4
Name: multiserialviewer
Version: 25.9.0
Summary: Shows multiple serial text streams in a single window with individual highlighting options.
Project-URL: GitHub, https://github.com/shaag7967/multiserialviewer
Project-URL: Homepage, https://github.com/shaag7967/multiserialviewer
Author: shaag
License:                     GNU GENERAL PUBLIC LICENSE
License-File: LICENSE
Keywords: MCU,UART,debug output,serial
Classifier: Development Status :: 2 - Pre-Alpha
Classifier: License :: OSI Approved :: GNU General Public License v3 (GPLv3)
Classifier: Programming Language :: Python :: 3.10
Classifier: Programming Language :: Python :: 3.11
Classifier: Programming Language :: Python :: 3.12
Classifier: Topic :: Software Development :: Embedded Systems
Classifier: Topic :: Terminals :: Serial
Classifier: Topic :: Utilities
Requires-Python: >=3.10
Requires-Dist: platformdirs==4.3.6
Requires-Dist: pyside6==6.8.1
